filesplitor.py
filesplitor-0.2.0.dist-info/LICENSE
filesplitor-0.2.0.dist-info/METADATA
filesplitor-0.2.0.dist-info/WHEEL
filesplitor-0.2.0.dist-info/entry_points.txt
filesplitor-0.2.0.dist-info/top_level.txt
filesplitor-0.2.0.dist-info/RECORD
